pytest_mccabe.py
pytest_mccabe-2.0.dist-info/LICENSE
pytest_mccabe-2.0.dist-info/METADATA
pytest_mccabe-2.0.dist-info/WHEEL
pytest_mccabe-2.0.dist-info/entry_points.txt
pytest_mccabe-2.0.dist-info/top_level.txt
pytest_mccabe-2.0.dist-info/zip-safe
pytest_mccabe-2.0.dist-info/RECORD
