Metadata-Version: 2.1
Name: pytest-mccabe
Version: 2.0
Summary: pytest plugin to run the mccabe code complexity checker.
Home-page: https://github.com/The-Compiler/pytest-mccabe
Author: Florian Bruhin
Author-email: me@the-compiler.org
License: MIT license
Keywords: pytest plugin mccabe complexity
Platform: UNKNOWN
Classifier: Environment :: Plugins
Classifier: Development Status :: 3 - Alpha
Classifier: Intended Audience :: Developers
Classifier: License :: OSI Approved :: MIT License
Classifier: Operating System :: OS Independent
Classifier: Programming Language :: Python :: 3
Classifier: Programming Language :: Python :: 3.5
Classifier: Programming Language :: Python :: 3.6
Classifier: Programming Language :: Python :: 3.7
Classifier: Programming Language :: Python :: 3.8
Classifier: Topic :: Software Development :: Quality Assurance
Classifier: Topic :: Software Development :: Testing
Requires-Dist: pytest (>=5.4.0)
Requires-Dist: mccabe
